{
  "image_id": 18,
  "source": "Dataset/img_18_c2of2.jpg",
  "column": 2,
  "total_columns": 2,
  "crop": {
    "x": 0,
    "y": 0,
    "w": 420,
    "h": 1466
  },
  "num_lines": 46,
  "lines": [
    {
      "id": 1,
      "bbox_global": {
        "x": 8,
        "y": 7,
        "w": 386,
        "h": 54
      },
      "bbox_local": {
        "x": 8,
        "y": 7,
        "w": 386,
        "h": 54
      }
    },
    {
      "id": 2,
      "bbox_global": {
        "x": 6,
        "y": 40,
        "w": 395,
        "h": 51
      },
      "bbox_local": {
        "x": 6,
        "y": 40,
        "w": 395,
        "h": 51
      }
    },
    {
      "id": 3,
      "bbox_global": {
        "x": 8,
        "y": 77,
        "w": 387,
        "h": 47
      },
      "bbox_local": {
        "x": 8,
        "y": 77,
        "w": 387,
        "h": 47
      }
    },
    {
      "id": 4,
      "bbox_global": {
        "x": 11,
        "y": 110,
        "w": 385,
        "h": 51
      },
      "bbox_local": {
        "x": 11,
        "y": 110,
        "w": 385,
        "h": 51
      }
    },
    {
      "id": 5,
      "bbox_global": {
        "x": 12,
        "y": 147,
        "w": 306,
        "h": 47
      },
      "bbox_local": {
        "x": 12,
        "y": 147,
        "w": 306,
        "h": 47
      }
    },
    {
      "id": 6,
      "bbox_global": {
        "x": 12,
        "y": 161,
        "w": 385,
        "h": 62
      },
      "bbox_local": {
        "x": 12,
        "y": 161,
        "w": 385,
        "h": 62
      }
    },
    {
      "id": 7,
      "bbox_global": {
        "x": 5,
        "y": 214,
        "w": 396,
        "h": 54
      },
      "bbox_local": {
        "x": 5,
        "y": 214,
        "w": 396,
        "h": 54
      }
    },
    {
      "id": 8,
      "bbox_global": {
        "x": 12,
        "y": 251,
        "w": 385,
        "h": 51
      },
      "bbox_local": {
        "x": 12,
        "y": 251,
        "w": 385,
        "h": 51
      }
    },
    {
      "id": 9,
      "bbox_global": {
        "x": 8,
        "y": 290,
        "w": 390,
        "h": 45
      },
      "bbox_local": {
        "x": 8,
        "y": 290,
        "w": 390,
        "h": 45
      }
    },
    {
      "id": 10,
      "bbox_global": {
        "x": 8,
        "y": 310,
        "w": 390,
        "h": 81
      },
      "bbox_local": {
        "x": 8,
        "y": 310,
        "w": 390,
        "h": 81
      }
    },
    {
      "id": 11,
      "bbox_global": {
        "x": 9,
        "y": 365,
        "w": 393,
        "h": 42
      },
      "bbox_local": {
        "x": 9,
        "y": 365,
        "w": 393,
        "h": 42
      }
    },
    {
      "id": 12,
      "bbox_global": {
        "x": 12,
        "y": 399,
        "w": 399,
        "h": 41
      },
      "bbox_local": {
        "x": 12,
        "y": 399,
        "w": 399,
        "h": 41
      }
    },
    {
      "id": 13,
      "bbox_global": {
        "x": 12,
        "y": 432,
        "w": 383,
        "h": 44
      },
      "bbox_local": {
        "x": 12,
        "y": 432,
        "w": 383,
        "h": 44
      }
    },
    {
      "id": 14,
      "bbox_global": {
        "x": 12,
        "y": 462,
        "w": 397,
        "h": 62
      },
      "bbox_local": {
        "x": 12,
        "y": 462,
        "w": 397,
        "h": 62
      }
    },
    {
      "id": 15,
      "bbox_global": {
        "x": 8,
        "y": 501,
        "w": 383,
        "h": 61
      },
      "bbox_local": {
        "x": 8,
        "y": 501,
        "w": 383,
        "h": 61
      }
    },
    {
      "id": 16,
      "bbox_global": {
        "x": 6,
        "y": 534,
        "w": 397,
        "h": 55
      },
      "bbox_local": {
        "x": 6,
        "y": 534,
        "w": 397,
        "h": 55
      }
    },
    {
      "id": 17,
      "bbox_global": {
        "x": 6,
        "y": 564,
        "w": 400,
        "h": 71
      },
      "bbox_local": {
        "x": 6,
        "y": 564,
        "w": 400,
        "h": 71
      }
    },
    {
      "id": 18,
      "bbox_global": {
        "x": 13,
        "y": 611,
        "w": 396,
        "h": 45
      },
      "bbox_local": {
        "x": 13,
        "y": 611,
        "w": 396,
        "h": 45
      }
    },
    {
      "id": 19,
      "bbox_global": {
        "x": 11,
        "y": 637,
        "w": 395,
        "h": 60
      },
      "bbox_local": {
        "x": 11,
        "y": 637,
        "w": 395,
        "h": 60
      }
    },
    {
      "id": 20,
      "bbox_global": {
        "x": 15,
        "y": 675,
        "w": 377,
        "h": 48
      },
      "bbox_local": {
        "x": 15,
        "y": 675,
        "w": 377,
        "h": 48
      }
    },
    {
      "id": 21,
      "bbox_global": {
        "x": 18,
        "y": 715,
        "w": 385,
        "h": 44
      },
      "bbox_local": {
        "x": 18,
        "y": 715,
        "w": 385,
        "h": 44
      }
    },
    {
      "id": 22,
      "bbox_global": {
        "x": 15,
        "y": 748,
        "w": 393,
        "h": 48
      },
      "bbox_local": {
        "x": 15,
        "y": 748,
        "w": 393,
        "h": 48
      }
    },
    {
      "id": 23,
      "bbox_global": {
        "x": 13,
        "y": 783,
        "w": 402,
        "h": 51
      },
      "bbox_local": {
        "x": 13,
        "y": 783,
        "w": 402,
        "h": 51
      }
    },
    {
      "id": 24,
      "bbox_global": {
        "x": 12,
        "y": 816,
        "w": 392,
        "h": 54
      },
      "bbox_local": {
        "x": 12,
        "y": 816,
        "w": 392,
        "h": 54
      }
    },
    {
      "id": 25,
      "bbox_global": {
        "x": 16,
        "y": 858,
        "w": 385,
        "h": 50
      },
      "bbox_local": {
        "x": 16,
        "y": 858,
        "w": 385,
        "h": 50
      }
    },
    {
      "id": 26,
      "bbox_global": {
        "x": 16,
        "y": 894,
        "w": 386,
        "h": 41
      },
      "bbox_local": {
        "x": 16,
        "y": 894,
        "w": 386,
        "h": 41
      }
    },
    {
      "id": 27,
      "bbox_global": {
        "x": 9,
        "y": 934,
        "w": 397,
        "h": 50
      },
      "bbox_local": {
        "x": 9,
        "y": 934,
        "w": 397,
        "h": 50
      }
    },
    {
      "id": 28,
      "bbox_global": {
        "x": 15,
        "y": 973,
        "w": 382,
        "h": 47
      },
      "bbox_local": {
        "x": 15,
        "y": 973,
        "w": 382,
        "h": 47
      }
    },
    {
      "id": 29,
      "bbox_global": {
        "x": 16,
        "y": 1009,
        "w": 303,
        "h": 51
      },
      "bbox_local": {
        "x": 16,
        "y": 1009,
        "w": 303,
        "h": 51
      }
    },
    {
      "id": 30,
      "bbox_global": {
        "x": 9,
        "y": 1042,
        "w": 336,
        "h": 67
      },
      "bbox_local": {
        "x": 9,
        "y": 1042,
        "w": 336,
        "h": 67
      }
    },
    {
      "id": 31,
      "bbox_global": {
        "x": 297,
        "y": 994,
        "w": 122,
        "h": 101
      },
      "bbox_local": {
        "x": 297,
        "y": 994,
        "w": 122,
        "h": 101
      }
    },
    {
      "id": 32,
      "bbox_global": {
        "x": 18,
        "y": 1073,
        "w": 383,
        "h": 52
      },
      "bbox_local": {
        "x": 18,
        "y": 1073,
        "w": 383,
        "h": 52
      }
    },
    {
      "id": 33,
      "bbox_global": {
        "x": 18,
        "y": 1115,
        "w": 382,
        "h": 54
      },
      "bbox_local": {
        "x": 18,
        "y": 1115,
        "w": 382,
        "h": 54
      }
    },
    {
      "id": 34,
      "bbox_global": {
        "x": 21,
        "y": 1156,
        "w": 372,
        "h": 47
      },
      "bbox_local": {
        "x": 21,
        "y": 1156,
        "w": 372,
        "h": 47
      }
    },
    {
      "id": 35,
      "bbox_global": {
        "x": 18,
        "y": 1198,
        "w": 380,
        "h": 38
      },
      "bbox_local": {
        "x": 18,
        "y": 1198,
        "w": 380,
        "h": 38
      }
    },
    {
      "id": 36,
      "bbox_global": {
        "x": 16,
        "y": 1225,
        "w": 385,
        "h": 54
      },
      "bbox_local": {
        "x": 16,
        "y": 1225,
        "w": 385,
        "h": 54
      }
    },
    {
      "id": 37,
      "bbox_global": {
        "x": 21,
        "y": 1259,
        "w": 386,
        "h": 52
      },
      "bbox_local": {
        "x": 21,
        "y": 1259,
        "w": 386,
        "h": 52
      }
    },
    {
      "id": 38,
      "bbox_global": {
        "x": 21,
        "y": 1304,
        "w": 380,
        "h": 40
      },
      "bbox_local": {
        "x": 21,
        "y": 1304,
        "w": 380,
        "h": 40
      }
    },
    {
      "id": 39,
      "bbox_global": {
        "x": 111,
        "y": 1350,
        "w": 35,
        "h": 32
      },
      "bbox_local": {
        "x": 111,
        "y": 1350,
        "w": 35,
        "h": 32
      }
    },
    {
      "id": 40,
      "bbox_global": {
        "x": 201,
        "y": 1345,
        "w": 57,
        "h": 34
      },
      "bbox_local": {
        "x": 201,
        "y": 1345,
        "w": 57,
        "h": 34
      }
    },
    {
      "id": 41,
      "bbox_global": {
        "x": 11,
        "y": 1378,
        "w": 11,
        "h": 11
      },
      "bbox_local": {
        "x": 11,
        "y": 1378,
        "w": 11,
        "h": 11
      }
    },
    {
      "id": 42,
      "bbox_global": {
        "x": 18,
        "y": 1352,
        "w": 94,
        "h": 42
      },
      "bbox_local": {
        "x": 18,
        "y": 1352,
        "w": 94,
        "h": 42
      }
    },
    {
      "id": 43,
      "bbox_global": {
        "x": 129,
        "y": 1348,
        "w": 75,
        "h": 45
      },
      "bbox_local": {
        "x": 129,
        "y": 1348,
        "w": 75,
        "h": 45
      }
    },
    {
      "id": 44,
      "bbox_global": {
        "x": 251,
        "y": 1331,
        "w": 158,
        "h": 51
      },
      "bbox_local": {
        "x": 251,
        "y": 1331,
        "w": 158,
        "h": 51
      }
    },
    {
      "id": 45,
      "bbox_global": {
        "x": 22,
        "y": 1371,
        "w": 386,
        "h": 54
      },
      "bbox_local": {
        "x": 22,
        "y": 1371,
        "w": 386,
        "h": 54
      }
    },
    {
      "id": 46,
      "bbox_global": {
        "x": 25,
        "y": 1417,
        "w": 372,
        "h": 40
      },
      "bbox_local": {
        "x": 25,
        "y": 1417,
        "w": 372,
        "h": 40
      }
    }
  ]
}